[
    {
        "name": "Абха",
        "latitude": 18.21639,
        "longitude": 42.50528
    },
    {
        "name": "Аль-Маджарида",
        "latitude": 19.12361,
        "longitude": 41.91111
    },
    {
        "name": "Аль-Кахаб",
        "latitude": 18.9256,
        "longitude": 41.955
    },
    {
        "name": "Хамис Мушаит",
        "latitude": 18.3,
        "longitude": 42.73333
    },
    {
        "name": "Мария",
        "latitude": 18.85,
        "longitude": 41.9667
    },
    {
        "name": "Миф",
        "latitude": 18.8917,
        "longitude": 41.9633
    },
    {
        "name": "Мунайзир",
        "latitude": 18.9464,
        "longitude": 41.9164
    },
    {
        "name": "Табала",
        "latitude": 19.95,
        "longitude": 42.4
    },
    {
        "name": "Аль-Баха",
        "latitude": 20.01288,
        "longitude": 41.46767
    },
    {
        "name": "Аль Миндак",
        "latitude": 20.1588,
        "longitude": 41.28337
    },
    {
        "name": "Хаджра",
        "latitude": 20.23333333,
        "longitude": 41.05
    },
    {
        "name": "Аль-Исавия",
        "latitude": 30.71681,
        "longitude": 37.97767
    },
    {
        "name": "Аль-Хадис",
        "latitude": 31.456011,
        "longitude": 37.14814
    },
    {
        "name": "Привет, Аммар",
        "latitude": 29.15944444,
        "longitude": 36.075
    },
    {
        "name": "Курайят",
        "latitude": 31.33176,
        "longitude": 37.34282
    },
    {
        "name": "Сакака",
        "latitude": 29.96974,
        "longitude": 40.20641
    },
    {
        "name": "Шувайр",
        "latitude": 30.11713,
        "longitude": 40.38925
    },
    {
        "name": "Табарджал",
        "latitude": 30.5,
        "longitude": 38.2167
    },
    {
        "name": "Тубарьял",
        "latitude": 30.49987,
        "longitude": 38.21603
    },
    {
        "name": "`` Аджмия",
        "latitude": 24.2167,
        "longitude": 38.5
    },
    {
        "name": "`Аля'",
        "latitude": 23.8236,
        "longitude": 38.8833
    },
    {
        "name": "`` Вот и все",
        "latitude": 23.5,
        "longitude": 38.9167
    },
    {
        "name": "`` Поторопитесь",
        "latitude": 24.0186,
        "longitude": 39.6731
    },
    {
        "name": "Абу Шайтана",
        "latitude": 23.8667,
        "longitude": 38.3667
    },
    {
        "name": "Абьяр Али",
        "latitude": 24.41666667,
        "longitude": 39.55
    },
    {
        "name": "Реклама в первую очередь",
        "latitude": 24.7667,
        "longitude": 39.5333
    },
    {
        "name": "Аль Авали",
        "latitude": 24.45,
        "longitude": 39.6167
    },
    {
        "name": "Аль Укул",
        "latitude": 24.5,
        "longitude": 39.8167
    },
    {
        "name": "Аль-Ахал",
        "latitude": 23.3156,
        "longitude": 39.8594
    },
    {
        "name": "Аль-Бардия",
        "latitude": 24.0439,
        "longitude": 39.6061
    },
    {
        "name": "Аль-Бика'",
        "latitude": 24.38861111,
        "longitude": 38.59888889
    },
    {
        "name": "Аль Бустан",
        "latitude": 23.2783,
        "longitude": 39.2428
    },
    {
        "name": "Аль Факира",
        "latitude": 23.4217,
        "longitude": 39.7097
    },
    {
        "name": "Аль Фурайш",
        "latitude": 24.22,
        "longitude": 39.2814
    },
    {
        "name": "Аль-Джабрия",
        "latitude": 24.25,
        "longitude": 38.5167
    },
    {
        "name": "Аль-Джесса",
        "latitude": 23.3333,
        "longitude": 40.3
    },
    {
        "name": "Аль Харма'",
        "latitude": 23.9,
        "longitude": 38.9
    },
    {
        "name": "Аль-Мальбана",
        "latitude": 23.1833,
        "longitude": 39.5167
    },
    {
        "name": "Аль Муфрихат",
        "latitude": 24.35,
        "longitude": 39.4167
    },
    {
        "name": "Аль-Мультаса",
        "latitude": 24.0833,
        "longitude": 38.15
    },
    {
        "name": "Аль-Мусайжид",
        "latitude": 24.0833,
        "longitude": 39.1
    },
    {
        "name": "Аль Вудай",
        "latitude": 24.1789,
        "longitude": 39.5481
    },
    {
        "name": "Аль-Джафр",
        "latitude": 25.41666667,
        "longitude": 49.61666667
    },
    {
        "name": "Аль-Ула",
        "latitude": 26.60853,
        "longitude": 37.92316
    },
    {
        "name": "Как Садайир",
        "latitude": 24.25,
        "longitude": 39.1833
    },
    {
        "name": "Урожай'",
        "latitude": 24.01277778,
        "longitude": 38.92277778
    },
    {
        "name": "Как Сумарийа",
        "latitude": 24.9214,
        "longitude": 39.6178
    },
    {
        "name": "Как Сувайрикия",
        "latitude": 23.35,
        "longitude": 40.3167
    },
    {
        "name": "Эш Шуфайя",
        "latitude": 23.8167,
        "longitude": 39.15
    },
    {
        "name": "ассирийский",
        "latitude": 24.3333,
        "longitude": 38.6333
    },
    {
        "name": "Бака",
        "latitude": 24.21666667,
        "longitude": 38.71666667
    },
    {
        "name": "Бартия",
        "latitude": 24.2833,
        "longitude": 38.5833
    },
    {
        "name": "Кстати",
        "latitude": 24.21666667,
        "longitude": 39.55
    },
    {
        "name": "Бирка",
        "latitude": 23.8203,
        "longitude": 38.8597
    },
    {
        "name": "Далеко",
        "latitude": 23.8167,
        "longitude": 38.8667
    },
    {
        "name": "Фиджи",
        "latitude": 24.26666667,
        "longitude": 38.56666667
    },
    {
        "name": "Хартия",
        "latitude": 24.25,
        "longitude": 38.55
    },
    {
        "name": "Хайлат Ради аль-Бахам",
        "latitude": 24.0839,
        "longitude": 39.725
    },
    {
        "name": "Хусайния",
        "latitude": 23.86666667,
        "longitude": 38.9
    },
    {
        "name": "Джадида",
        "latitude": 23.8167,
        "longitude": 38.8333
    },
    {
        "name": "Хайф Фадил",
        "latitude": 24.2667,
        "longitude": 38.5667
    },
    {
        "name": "Мадсус",
        "latitude": 24.35,
        "longitude": 38.55
    },
    {
        "name": "Махаттат аль-Хафах",
        "latitude": 23.75,
        "longitude": 39.3
    },
    {
        "name": "Макра",
        "latitude": 24.4167,
        "longitude": 38.7
    },
    {
        "name": "Макшуш",
        "latitude": 23.5833,
        "longitude": 38.6
    },
    {
        "name": "Английский",
        "latitude": 24.0333,
        "longitude": 38.2333
    },
    {
        "name": "Мавара",
        "latitude": 24.2,
        "longitude": 38.4333
    },
    {
        "name": "Медина",
        "latitude": 24.46861,
        "longitude": 39.61417
    },
    {
        "name": "Милха",
        "latitude": 24.05,
        "longitude": 38.3
    },
    {
        "name": "Нуджайл",
        "latitude": 24.2667,
        "longitude": 38.65
    },
    {
        "name": "держать",
        "latitude": 24.4,
        "longitude": 39.65
    },
    {
        "name": "Райис",
        "latitude": 23.5667,
        "longitude": 38.6
    },
    {
        "name": "да",
        "latitude": 24.23333333,
        "longitude": 38.53333333
    },
    {
        "name": "Сиди Хамза",
        "latitude": 24.5,
        "longitude": 39.6167
    },
    {
        "name": "Рынок Сувайк",
        "latitude": 24.3667,
        "longitude": 38.45
    },
    {
        "name": "Сукубия",
        "latitude": 24.2333,
        "longitude": 38.5
    },
    {
        "name": "Сувада",
        "latitude": 24.0333,
        "longitude": 38.2
    },
    {
        "name": "Воля",
        "latitude": 23.8833,
        "longitude": 38.9
    },
    {
        "name": "Янбу",
        "latitude": 24.08954,
        "longitude": 38.0618
    },
    {
        "name": "Ад Дхия",
        "latitude": 26.027,
        "longitude": 43.157
    },
    {
        "name": "Аль-Букайрия",
        "latitude": 26.13915,
        "longitude": 43.65782
    },
    {
        "name": "Аль Фувайлик",
        "latitude": 26.4436,
        "longitude": 43.25164
    },
    {
        "name": "Аль Митнаб",
        "latitude": 25.86012,
        "longitude": 44.22228
    },
    {
        "name": "Аль-Фибия",
        "latitude": 26.027,
        "longitude": 43.157
    },
    {
        "name": "Ар Расс",
        "latitude": 25.86944,
        "longitude": 43.4973
    },
    {
        "name": "Бурайда",
        "latitude": 26.33333333,
        "longitude": 43.96666667
    },
    {
        "name": "Бурайда",
        "latitude": 26.32599,
        "longitude": 43.97497
    },
    {
        "name": "Духна",
        "latitude": 25.35621,
        "longitude": 43.62268
    },
    {
        "name": "Киба",
        "latitude": 27.40285,
        "longitude": 44.3277
    },
    {
        "name": "Танума",
        "latitude": 27.1,
        "longitude": 44.13333
    },
    {
        "name": "Ср Алнкил",
        "latitude": 25.4267,
        "longitude": 42.8343
    },
    {
        "name": "Абкайк",
        "latitude": 25.93402,
        "longitude": 49.6688
    },
    {
        "name": "Аль-Авджам",
        "latitude": 26.56324,
        "longitude": 49.94331
    },
    {
        "name": "Аль-Бацалия",
        "latitude": 25.43333,
        "longitude": 49.63333
    },
    {
        "name": "Аль-Хуфуф",
        "latitude": 25.36467,
        "longitude": 49.58764
    },
    {
        "name": "Аль-Джафр",
        "latitude": 25.37736,
        "longitude": 49.72154
    },
    {
        "name": "Аль-Джубайль",
        "latitude": 27.0174,
        "longitude": 49.62251
    },
    {
        "name": "Аль Хафджи",
        "latitude": 28.43905,
        "longitude": 48.49132
    },
    {
        "name": "Аль Марказ",
        "latitude": 25.4,
        "longitude": 49.73333
    },
    {
        "name": "Аль Мубарраз",
        "latitude": 25.40768,
        "longitude": 49.59028
    },
    {
        "name": "Аль-Мунайзила",
        "latitude": 25.38333,
        "longitude": 49.66667
    },
    {
        "name": "Аль Мутайрифи",
        "latitude": 25.47878,
        "longitude": 49.55824
    },
    {
        "name": "Аль-Кара",
        "latitude": 25.41667,
        "longitude": 49.66667
    },
    {
        "name": "Аль-Катиф",
        "latitude": 26.56542,
        "longitude": 50.0089
    },
    {
        "name": "Аль-Курейн",
        "latitude": 25.48333,
        "longitude": 49.6
    },
    {
        "name": "Аль-Убайла",
        "latitude": 21.98417,
        "longitude": 50.93966
    },
    {
        "name": "Аль-Авамия",
        "latitude": 26.583333,
        "longitude": 49.983333
    },
    {
        "name": "Аль-Авджам",
        "latitude": 26.5583,
        "longitude": 49.9503
    },
    {
        "name": "Аль-Мубарраз",
        "latitude": 25.4416,
        "longitude": 49.6642
    },
    {
        "name": "Ас Саффания",
        "latitude": 27.97083,
        "longitude": 48.73
    },
    {
        "name": "Ац Тараф",
        "latitude": 25.36232,
        "longitude": 49.72757
    },
    {
        "name": "В Туби",
        "latitude": 26.55778,
        "longitude": 49.99167
    },
    {
        "name": "Даммам",
        "latitude": 26.43442,
        "longitude": 50.10326
    },
    {
        "name": "Дхахран",
        "latitude": 26.28864,
        "longitude": 50.11396
    },
    {
        "name": "Град",
        "latitude": 27.51666667,
        "longitude": 41.68333333
    },
    {
        "name": "Хафар аль-Батин",
        "latitude": 28.43279,
        "longitude": 45.97077
    },
    {
        "name": "Харрис",
        "latitude": 24.14555556,
        "longitude": 49.06527778
    },
    {
        "name": "Июль",
        "latitude": 25.5,
        "longitude": 49.6
    },
    {
        "name": "Хобар",
        "latitude": 26.27944,
        "longitude": 50.20833
    },
    {
        "name": "Мулайджа",
        "latitude": 27.27103,
        "longitude": 48.42419
    },
    {
        "name": "Нария",
        "latitude": 27.4699,
        "longitude": 48.4844
    },
    {
        "name": "Кайсумах",
        "latitude": 28.31117,
        "longitude": 46.12729
    },
    {
        "name": "Рахима",
        "latitude": 26.70791,
        "longitude": 50.06194
    },
    {
        "name": "Шафва",
        "latitude": 26.6497,
        "longitude": 49.95522
    },
    {
        "name": "Сайхат",
        "latitude": 26.475,
        "longitude": 50.04166667
    },
    {
        "name": "Сюда",
        "latitude": 26.5733,
        "longitude": 50.04028
    },
    {
        "name": "Узаилия",
        "latitude": 25.1333,
        "longitude": 49.3
    },
    {
        "name": "Умм как Сахик",
        "latitude": 26.65361,
        "longitude": 49.91639
    },
    {
        "name": "Укаир",
        "latitude": 25.6431,
        "longitude": 50.2144
    },
    {
        "name": "Джубба",
        "latitude": 28.0062,
        "longitude": 40.9416
    },
    {
        "name": "Мавкак",
        "latitude": 27.38398,
        "longitude": 41.17635
    },
    {
        "name": "Куфар",
        "latitude": 27.41534,
        "longitude": 41.61903
    },
    {
        "name": "Останавливаться",
        "latitude": 26.49418,
        "longitude": 42.12494
    },
    {
        "name": "Абу Ариш",
        "latitude": 16.96887,
        "longitude": 42.83251
    },
    {
        "name": "Абу Радиф",
        "latitude": 16.6186,
        "longitude": 43.1311
    },
    {
        "name": "Объявление Дарб",
        "latitude": 17.72285,
        "longitude": 42.25261
    },
    {
        "name": "Ад Дурия",
        "latitude": 16.5842,
        "longitude": 42.8431
    },
    {
        "name": "и еще",
        "latitude": 16.6778,
        "longitude": 42.9592
    },
    {
        "name": "Аль Улайн",
        "latitude": 17.15,
        "longitude": 43.1708
    },
    {
        "name": "Аль-Усейла",
        "latitude": 16.9203,
        "longitude": 42.7353
    },
    {
        "name": "Аль Бадави",
        "latitude": 16.6333,
        "longitude": 42.865
    },
    {
        "name": "Аль-Хадур",
        "latitude": 16.5436,
        "longitude": 42.8672
    },
    {
        "name": "Аль Ханаша",
        "latitude": 16.5581,
        "longitude": 42.7653
    },
    {
        "name": "Аль Харани",
        "latitude": 16.775,
        "longitude": 42.9097
    },
    {
        "name": "Аль Хасама",
        "latitude": 16.68333333,
        "longitude": 42.92694444
    },
    {
        "name": "Аль-Хиджфар",
        "latitude": 16.5444,
        "longitude": 42.8472
    },
    {
        "name": "Аль Джади",
        "latitude": 16.645,
        "longitude": 42.9947
    },
    {
        "name": "Аль-Джарадия",
        "latitude": 16.57946,
        "longitude": 42.9124
    },
    {
        "name": "Аль-Джавах",
        "latitude": 16.9567,
        "longitude": 43.0297
    },
    {
        "name": "Аль-Джирба",
        "latitude": 16.9264,
        "longitude": 42.8861
    },
    {
        "name": "Аль Карбус",
        "latitude": 16.8733,
        "longitude": 42.6317
    },
    {
        "name": "Аль-Кавахила",
        "latitude": 16.9614,
        "longitude": 42.6725
    },
    {
        "name": "Аль Хадра Джизан",
        "latitude": 16.58583333,
        "longitude": 42.96333333
    },
    {
        "name": "Аль-Хараба Джизан",
        "latitude": 16.7558,
        "longitude": 42.9547
    },
    {
        "name": "Аль-Харадила",
        "latitude": 16.9272,
        "longitude": 42.6264
    },
    {
        "name": "Аль-Хашабия",
        "latitude": 16.9403,
        "longitude": 42.6431
    },
    {
        "name": "Аль-Хуба",
        "latitude": 16.7886,
        "longitude": 43.2219
    },
    {
        "name": "Аль Кирс",
        "latitude": 16.5772,
        "longitude": 42.9475
    },
    {
        "name": "Аль-Лукийя",
        "latitude": 16.6606,
        "longitude": 43.04
    },
    {
        "name": "Аль-Маайн",
        "latitude": 16.6108,
        "longitude": 43.1472
    },
    {
        "name": "Аль Мадайя",
        "latitude": 16.7697,
        "longitude": 42.7311
    },
    {
        "name": "Аль Мали",
        "latitude": 16.7953,
        "longitude": 42.9536
    },
    {
        "name": "Аль Маясам",
        "latitude": 16.9478,
        "longitude": 42.7211
    },
    {
        "name": "Аль-Каим",
        "latitude": 16.71944444,
        "longitude": 42.97666667
    },
    {
        "name": "Эл Лок",
        "latitude": 16.6733,
        "longitude": 43.0789
    },
    {
        "name": "Аль-Курайб",
        "latitude": 16.975,
        "longitude": 42.7253
    },
    {
        "name": "Аль-Кува",
        "latitude": 16.7994,
        "longitude": 43.225
    },
    {
        "name": "Аль Васили",
        "latitude": 16.9469,
        "longitude": 42.6903
    },
    {
        "name": "Ан-Наджамия",
        "latitude": 16.5647,
        "longitude": 42.9439
    },
    {
        "name": "Ар Рукуба",
        "latitude": 16.6222,
        "longitude": 42.9675
    },
    {
        "name": "Аш Шукайк",
        "latitude": 17.70305556,
        "longitude": 42.02944444
    },
    {
        "name": "Бахшат Ямани",
        "latitude": 16.8986,
        "longitude": 42.5989
    },
    {
        "name": "Фарасан",
        "latitude": 16.70222,
        "longitude": 42.11833
    },
    {
        "name": "Гавия",
        "latitude": 16.565,
        "longitude": 43.1108
    },
    {
        "name": "Хамайя",
        "latitude": 16.9894,
        "longitude": 43.1603
    },
    {
        "name": "Спасибо",
        "latitude": 16.7619,
        "longitude": 42.9222
    },
    {
        "name": "Джизан",
        "latitude": 16.88917,
        "longitude": 42.55111
    },
    {
        "name": "Привет Саудовская Аравия",
        "latitude": 16.6694,
        "longitude": 42.8922
    },
    {
        "name": "Калул",
        "latitude": 16.8975,
        "longitude": 42.8467
    },
    {
        "name": "Хабат Саид",
        "latitude": 16.9978,
        "longitude": 42.7322
    },
    {
        "name": "Халифа",
        "latitude": 16.5547,
        "longitude": 43.0894
    },
    {
        "name": "Хатиб Саудовская Аравия",
        "latitude": 16.8961,
        "longitude": 41.8575
    },
    {
        "name": "Хумсия",
        "latitude": 16.7714,
        "longitude": 42.8019
    },
    {
        "name": "счастье",
        "latitude": 16.88,
        "longitude": 43.1372
    },
    {
        "name": "величие",
        "latitude": 16.8333,
        "longitude": 43.1667
    },
    {
        "name": "нелюбимый",
        "latitude": 16.99777778,
        "longitude": 42.67388889
    },
    {
        "name": "Мислия",
        "latitude": 17.45988,
        "longitude": 42.5572
    },
    {
        "name": "Мижира",
        "latitude": 16.82611,
        "longitude": 42.73333
    },
    {
        "name": "Вы говорите",
        "latitude": 16.5936,
        "longitude": 43.0328
    },
    {
        "name": "Мундарак",
        "latitude": 16.7542,
        "longitude": 43.1489
    },
    {
        "name": "Мувасам",
        "latitude": 16.4167,
        "longitude": 42.8258
    },
    {
        "name": "Книга",
        "latitude": 17.3333,
        "longitude": 43.25
    },
    {
        "name": "власть",
        "latitude": 16.73333333,
        "longitude": 42.89027778
    },
    {
        "name": "Рахван",
        "latitude": 16.8333,
        "longitude": 43.2167
    },
    {
        "name": "Равха",
        "latitude": 16.9478,
        "longitude": 42.7933
    },
    {
        "name": "Шабья",
        "latitude": 17.1495,
        "longitude": 42.62537
    },
    {
        "name": "Садилия",
        "latitude": 16.9264,
        "longitude": 42.83
    },
    {
        "name": "Привет",
        "latitude": 16.9753,
        "longitude": 42.7564
    },
    {
        "name": "Шамита",
        "latitude": 16.59601,
        "longitude": 42.94435
    },
    {
        "name": "Абу Урва",
        "latitude": 21.65,
        "longitude": 39.7
    },
    {
        "name": "Абу Хисан",
        "latitude": 21.7306,
        "longitude": 39.7833
    },
    {
        "name": "Абу Кирфа",
        "latitude": 21.7667,
        "longitude": 39.6833
    },
    {
        "name": "Абу Шуайб",
        "latitude": 21.5833,
        "longitude": 39.7
    },
    {
        "name": "Ад Дабба",
        "latitude": 21.7167,
        "longitude": 39.8333
    },
    {
        "name": "Ад Даух",
        "latitude": 21.7722,
        "longitude": 39.7014
    },
    {
        "name": "Продолжительность рекламы",
        "latitude": 21.8167,
        "longitude": 39.7667
    },
    {
        "name": "Аль-Абар",
        "latitude": 21.0981,
        "longitude": 39.9103
    },
    {
        "name": "Аль Адл",
        "latitude": 21.44361,
        "longitude": 39.85611
    },
    {
        "name": "Аль Ашраф",
        "latitude": 21.5236,
        "longitude": 39.6167
    },
    {
        "name": "Аль Балад",
        "latitude": 21.4878,
        "longitude": 39.1936
    },
    {
        "name": "Аль Барабир",
        "latitude": 21.5203,
        "longitude": 39.6325
    },
    {
        "name": "Аль-Биар",
        "latitude": 22.64972222,
        "longitude": 39.67027778
    },
    {
        "name": "Эл Бирк",
        "latitude": 18.21631,
        "longitude": 41.53593
    },
    {
        "name": "Аль-Бурайка",
        "latitude": 21.7861,
        "longitude": 39.7167
    },
    {
        "name": "Аль-Фаввара",
        "latitude": 21.8328,
        "longitude": 40.1611
    },
    {
        "name": "Аль Файда",
        "latitude": 21.9844,
        "longitude": 39.3847
    },
    {
        "name": "Аль Фазз",
        "latitude": 21.9833,
        "longitude": 39.5222
    },
    {
        "name": "Аль Гарит",
        "latitude": 21.6,
        "longitude": 41.8833
    },
    {
        "name": "Аль-Гассала",
        "latitude": 21.45,
        "longitude": 39.8667
    },
    {
        "name": "Аль Гула",
        "latitude": 21.95,
        "longitude": 39.3167
    },
    {
        "name": "Аль Хада",
        "latitude": 21.36753,
        "longitude": 40.28694
    },
    {
        "name": "Аль Галака",
        "latitude": 21.35,
        "longitude": 40.45
    },
    {
        "name": "Аль-Хамима",
        "latitude": 21.5167,
        "longitude": 39.6333
    },
    {
        "name": "Аль Харра Мекка",
        "latitude": 21.95,
        "longitude": 39.48333333
    },
    {
        "name": "Аль-Хавия",
        "latitude": 21.42415,
        "longitude": 40.49303
    },
    {
        "name": "Аль-Искан",
        "latitude": 21.4,
        "longitude": 39.7833
    },
    {
        "name": "Аль-Джадида",
        "latitude": 21.6703,
        "longitude": 40.1264
    },
    {
        "name": "Аль-Джамия",
        "latitude": 21.4667,
        "longitude": 39.25
    },
    {
        "name": "Аль-Джид",
        "latitude": 21.9333,
        "longitude": 39.5833
    },
    {
        "name": "Аль Джурана",
        "latitude": 21.5667,
        "longitude": 39.95
    },
    {
        "name": "Аль-Джумум",
        "latitude": 21.61694,
        "longitude": 39.69806
    },
    {
        "name": "Аль Хадра Мекка",
        "latitude": 21.46777778,
        "longitude": 39.90472222
    },
    {
        "name": "Аль Халас",
        "latitude": 21.7,
        "longitude": 39.8
    },
    {
        "name": "Аль-Хамра",
        "latitude": 22.4333,
        "longitude": 39.4667
    },
    {
        "name": "Аль Хайдар",
        "latitude": 21.4694,
        "longitude": 40.6306
    },
    {
        "name": "Аль Хайф",
        "latitude": 21.6833,
        "longitude": 39.7333
    },
    {
        "name": "Аль Хуласа",
        "latitude": 21.6833,
        "longitude": 39.9167
    },
    {
        "name": "Аль-Кидва",
        "latitude": 21.7833,
        "longitude": 39.6833
    },
    {
        "name": "Аль Кура",
        "latitude": 21.8,
        "longitude": 39.1333
    },
    {
        "name": "Аль-Мараш",
        "latitude": 21.1333,
        "longitude": 40.6
    },
    {
        "name": "Аль-Мадик Мекка",
        "latitude": 21.6758,
        "longitude": 40.1308
    },
    {
        "name": "Аль Магал",
        "latitude": 21.9667,
        "longitude": 39.55
    },
    {
        "name": "Аль-Маджар",
        "latitude": 21.4333,
        "longitude": 39.2
    },
    {
        "name": "Аль-Макра",
        "latitude": 21.2667,
        "longitude": 39.95
    },
    {
        "name": "Аль Масарра",
        "latitude": 21.3667,
        "longitude": 40.4667
    },
    {
        "name": "Аль Масфала",
        "latitude": 21.4167,
        "longitude": 39.8167
    },
    {
        "name": "Аль Машаих",
        "latitude": 21.35,
        "longitude": 40.3333
    },
    {
        "name": "Аль Матна",
        "latitude": 21.26666667,
        "longitude": 40.38333333
    },
    {
        "name": "Аль Мубарак",
        "latitude": 21.7,
        "longitude": 39.9
    },
    {
        "name": "Аль Мудаввара",
        "latitude": 21.2667,
        "longitude": 39.9667
    },
    {
        "name": "Аль Мулайха'",
        "latitude": 21.8,
        "longitude": 40.35
    },
    {
        "name": "Аль-Мундасса",
        "latitude": 21.6333,
        "longitude": 39.7486
    },
    {
        "name": "Аль Мукайти",
        "latitude": 21.5486,
        "longitude": 39.7861
    },
    {
        "name": "Аль Мукр",
        "latitude": 22.0,
        "longitude": 39.3833
    },
    {
        "name": "Аль Мувайх",
        "latitude": 22.43333,
        "longitude": 41.75829
    },
    {
        "name": "Аль-Кадима",
        "latitude": 22.35,
        "longitude": 39.15
    },
    {
        "name": "Аль-Карара",
        "latitude": 21.4289,
        "longitude": 39.8281
    },
    {
        "name": "Аль Кариат",
        "latitude": 21.4667,
        "longitude": 39.2
    },
    {
        "name": "Аль-Кавбайя",
        "latitude": 21.6667,
        "longitude": 39.9833
    },
    {
        "name": "Аль-Киршан",
        "latitude": 21.5667,
        "longitude": 39.7
    },
    {
        "name": "Аль-Кутуба",
        "latitude": 21.9333,
        "longitude": 40.3667
    },
    {
        "name": "Аль-Куфаиф",
        "latitude": 21.8333,
        "longitude": 40.45
    },
    {
        "name": "Аль-Кушасия",
        "latitude": 21.4333,
        "longitude": 39.8333
    },
    {
        "name": "Аль-Ухайдир",
        "latitude": 21.9333,
        "longitude": 40.0167
    },
    {
        "name": "Аль Вахт",
        "latitude": 21.2333,
        "longitude": 40.35
    },
    {
        "name": "Ар Рабва в роли Блоу",
        "latitude": 21.9553,
        "longitude": 39.4367
    },
    {
        "name": "Ар Рафаах",
        "latitude": 21.5167,
        "longitude": 40.2
    },
    {
        "name": "Ар Равда аш Шамалия",
        "latitude": 21.7333,
        "longitude": 39.9667
    },
    {
        "name": "Ар-Рудайма",
        "latitude": 21.7667,
        "longitude": 39.6833
    },
    {
        "name": "Арья`",
        "latitude": 21.0856,
        "longitude": 40.6239
    },
    {
        "name": "Ас Садр",
        "latitude": 21.5189,
        "longitude": 40.1975
    },
    {
        "name": "Ас Самд аш Шамали",
        "latitude": 21.675,
        "longitude": 39.75
    },
    {
        "name": "Ас Сай аль-Кабир",
        "latitude": 21.6264,
        "longitude": 40.4153
    },
    {
        "name": "Как парус как Сагир",
        "latitude": 21.5064,
        "longitude": 40.4822
    },
    {
        "name": "Как Сифьяни",
        "latitude": 21.4756,
        "longitude": 39.8431
    },
    {
        "name": "Как Судайра Мекка",
        "latitude": 21.3619,
        "longitude": 40.8547
    },
    {
        "name": "Как Сувада",
        "latitude": 21.1339,
        "longitude": 40.5117
    },
    {
        "name": "Аш Шафа",
        "latitude": 21.0721,
        "longitude": 40.31185
    },
    {
        "name": "Эш Шаджва",
        "latitude": 21.6644,
        "longitude": 40.0114
    },
    {
        "name": "Аш Шамия",
        "latitude": 21.8411,
        "longitude": 39.5244
    },
    {
        "name": "Аш Шарай'",
        "latitude": 21.46305556,
        "longitude": 39.94611111
    },
    {
        "name": "Эш Шайби",
        "latitude": 21.6958,
        "longitude": 39.9417
    },
    {
        "name": "Аш Шиб",
        "latitude": 21.9689,
        "longitude": 39.4861
    },
    {
        "name": "Аш Шиша",
        "latitude": 21.3503,
        "longitude": 39.8919
    },
    {
        "name": "Эш Шумайси",
        "latitude": 21.5833,
        "longitude": 39.6833
    },
    {
        "name": "Эш Шувайбит",
        "latitude": 21.3797,
        "longitude": 40.5194
    },
    {
        "name": "В Таниме",
        "latitude": 21.4825,
        "longitude": 39.805
    },
    {
        "name": "В Тарфе",
        "latitude": 21.70638889,
        "longitude": 39.87138889
    },
    {
        "name": "Отец Турция",
        "latitude": 21.9492,
        "longitude": 39.4131
    },
    {
        "name": "Займа",
        "latitude": 21.6186,
        "longitude": 40.1133
    },
    {
        "name": "Зилал",
        "latitude": 21.4889,
        "longitude": 39.5942
    },
    {
        "name": "Зугба",
        "latitude": 21.7167,
        "longitude": 39.9458
    },
    {
        "name": "Зурра`",
        "latitude": 21.9106,
        "longitude": 39.4
    },
    {
        "name": "Зувайб",
        "latitude": 21.9167,
        "longitude": 39.9694
    },
    {
        "name": "Бахрат аль-Кадима",
        "latitude": 21.4133,
        "longitude": 39.4939
    },
    {
        "name": "Бахвил",
        "latitude": 22.4294,
        "longitude": 39.4294
    },
    {
        "name": "Барана",
        "latitude": 21.5542,
        "longitude": 39.8222
    },
    {
        "name": "Барза",
        "latitude": 21.98,
        "longitude": 39.6756
    },
    {
        "name": "Башм",
        "latitude": 21.4822,
        "longitude": 39.8208
    },
    {
        "name": "Бурайка",
        "latitude": 22.3444,
        "longitude": 39.32
    },
    {
        "name": "Бурайман",
        "latitude": 21.6375,
        "longitude": 39.2264
    },
    {
        "name": "ГОРОД ГАР",
        "latitude": 21.9738,
        "longitude": 39.3682
    },
    {
        "name": "Дабья",
        "latitude": 22.4247,
        "longitude": 39.4461
    },
    {
        "name": "Золотой",
        "latitude": 21.93333333,
        "longitude": 39.11666667
    },
    {
        "name": "Дугайбджа",
        "latitude": 22.5903,
        "longitude": 41.3597
    },
    {
        "name": "Файд",
        "latitude": 21.9172,
        "longitude": 39.3883
    },
    {
        "name": "Гаран",
        "latitude": 21.98027,
        "longitude": 39.36521
    },
    {
        "name": "Сейчас'",
        "latitude": 21.45027778,
        "longitude": 39.55444444
    },
    {
        "name": "Хаддат Эш Шам",
        "latitude": 21.7967,
        "longitude": 39.6833
    },
    {
        "name": "Хада",
        "latitude": 21.6525,
        "longitude": 40.0142
    },
    {
        "name": "Хаджур",
        "latitude": 23.0178,
        "longitude": 39.7303
    },
    {
        "name": "Страница",
        "latitude": 21.9542,
        "longitude": 39.7028
    },
    {
        "name": "Хусна",
        "latitude": 21.8,
        "longitude": 39.59166667
    },
    {
        "name": "Джарвал",
        "latitude": 21.4333,
        "longitude": 39.8167
    },
    {
        "name": "Джидда",
        "latitude": 21.54238,
        "longitude": 39.19797
    },
    {
        "name": "Июль",
        "latitude": 21.9583,
        "longitude": 39.7583
    },
    {
        "name": "Хумра",
        "latitude": 21.3728,
        "longitude": 39.2261
    },
    {
        "name": "Kulakh",
        "latitude": 21.2964,
        "longitude": 40.7969
    },
    {
        "name": "Медрака",
        "latitude": 21.9797,
        "longitude": 39.9875
    },
    {
        "name": "Мафурк",
        "latitude": 21.5222,
        "longitude": 40.1794
    },
    {
        "name": "Малакан",
        "latitude": 21.2158,
        "longitude": 39.9503
    },
    {
        "name": "Машаджи",
        "latitude": 21.7389,
        "longitude": 39.9667
    },
    {
        "name": "Церковь Махд аль-Хайль",
        "latitude": 21.9417,
        "longitude": 39.8861
    },
    {
        "name": "черви",
        "latitude": 21.75,
        "longitude": 40.3164
    },
    {
        "name": "Матия",
        "latitude": 21.5417,
        "longitude": 39.8194
    },
    {
        "name": "Мекка",
        "latitude": 21.42664,
        "longitude": 39.82563
    },
    {
        "name": "Мина",
        "latitude": 21.41333333,
        "longitude": 39.89333333
    },
    {
        "name": "Муршидия",
        "latitude": 21.4889,
        "longitude": 39.7944
    },
    {
        "name": "Мушриф",
        "latitude": 22.6292,
        "longitude": 41.3567
    },
    {
        "name": "Нугайшия",
        "latitude": 21.2167,
        "longitude": 40.75
    },
    {
        "name": "Нузлат аль Факин",
        "latitude": 22.0,
        "longitude": 39.4167
    },
    {
        "name": "Склон",
        "latitude": 21.0667,
        "longitude": 41.0167
    },
    {
        "name": "Кувейза",
        "latitude": 21.4903,
        "longitude": 39.2767
    },
    {
        "name": "Рабиг",
        "latitude": 22.79856,
        "longitude": 39.03493
    },
    {
        "name": "Рабва Ган",
        "latitude": 21.9833,
        "longitude": 39.4167
    },
    {
        "name": "Ракия",
        "latitude": 21.7667,
        "longitude": 40.35
    },
    {
        "name": "Он нашел это",
        "latitude": 21.5833,
        "longitude": 40.1167
    },
    {
        "name": "Шиб Амир",
        "latitude": 21.4333,
        "longitude": 39.8333
    },
    {
        "name": "Шираайн",
        "latitude": 21.2833,
        "longitude": 40.7833
    },
    {
        "name": "Соломон",
        "latitude": 22.5833,
        "longitude": 39.6333
    },
    {
        "name": "Сумайма",
        "latitude": 21.25,
        "longitude": 39.1667
    },
    {
        "name": "Сувейс",
        "latitude": 21.95,
        "longitude": 39.9667
    },
    {
        "name": "Таиф",
        "latitude": 21.27028,
        "longitude": 40.41583
    },
    {
        "name": "Тарва",
        "latitude": 21.5167,
        "longitude": 39.6167
    },
    {
        "name": "Тувал",
        "latitude": 22.28333333,
        "longitude": 39.1
    },
    {
        "name": "Тураба",
        "latitude": 21.21406,
        "longitude": 41.6331
    },
    {
        "name": "Усфан",
        "latitude": 21.92306,
        "longitude": 39.35594
    },
    {
        "name": "Вади аль-Джалиль",
        "latitude": 21.4667,
        "longitude": 39.85
    },
    {
        "name": "Наджран",
        "latitude": 17.49326,
        "longitude": 44.12766
    },
    {
        "name": "звонки",
        "latitude": 30.97531,
        "longitude": 41.03808
    },
    {
        "name": "Нисаб",
        "latitude": 29.19274,
        "longitude": 44.71598
    },
    {
        "name": "Тураиф",
        "latitude": 31.67252,
        "longitude": 38.66374
    },
    {
        "name": "Умм Радама",
        "latitude": 28.67985,
        "longitude": 44.69549
    },
    {
        "name": "Ад Давадими",
        "latitude": 24.50772,
        "longitude": 44.39237
    },
    {
        "name": "Диле",
        "latitude": 23.99104,
        "longitude": 47.16181
    },
    {
        "name": "Афиф",
        "latitude": 23.9065,
        "longitude": 42.91724
    },
    {
        "name": "Айн Аль-Бараха",
        "latitude": 24.75806,
        "longitude": 43.77389
    },
    {
        "name": "Аль-Арцавия",
        "latitude": 26.50387,
        "longitude": 45.34813
    },
    {
        "name": "Аль Бир",
        "latitude": 25.3,
        "longitude": 45.9667
    },
    {
        "name": "Аль Хейр",
        "latitude": 24.39072,
        "longitude": 46.98677
    },
    {
        "name": "Аль-Джурайфа",
        "latitude": 25.52932,
        "longitude": 45.25644
    },
    {
        "name": "Аль Хардж",
        "latitude": 24.15541,
        "longitude": 47.33457
    },
    {
        "name": "Ар Рейн",
        "latitude": 23.54995,
        "longitude": 45.50463
    },
    {
        "name": "Ас Саламия",
        "latitude": 24.20154,
        "longitude": 47.28872
    },
    {
        "name": "Ас Сулайил",
        "latitude": 20.46067,
        "longitude": 45.57792
    },
    {
        "name": "Зульфи",
        "latitude": 26.29945,
        "longitude": 44.81542
    },
    {
        "name": "Давадми",
        "latitude": 24.50772,
        "longitude": 44.39237
    },
    {
        "name": "Дирия",
        "latitude": 24.75187,
        "longitude": 46.53874
    },
    {
        "name": "Хармах",
        "latitude": 25.91666667,
        "longitude": 45.33333333
    },
    {
        "name": "Джаладжил",
        "latitude": 25.66666667,
        "longitude": 45.45
    },
    {
        "name": "Лейла",
        "latitude": 22.2833,
        "longitude": 46.7333
    },
    {
        "name": "Манфуха",
        "latitude": 24.59611111,
        "longitude": 46.72722222
    },
    {
        "name": "Марат",
        "latitude": 25.07064,
        "longitude": 45.45775
    },
    {
        "name": "хотя",
        "latitude": 24.07746,
        "longitude": 47.1659
    },
    {
        "name": "Эр-Рияд",
        "latitude": 24.68773,
        "longitude": 46.72185
    },
    {
        "name": "Это отстой",
        "latitude": 25.18251,
        "longitude": 44.59964
    },
    {
        "name": "Шохайб",
        "latitude": 24.49023,
        "longitude": 46.26871
    },
    {
        "name": "Молоток",
        "latitude": 25.70347,
        "longitude": 45.86835
    },
    {
        "name": "Аль-Ваджх",
        "latitude": 26.24551,
        "longitude": 36.45249
    },
    {
        "name": "Смотреть",
        "latitude": 27.35134,
        "longitude": 35.69014
    },
    {
        "name": "Табу",
        "latitude": 28.3998,
        "longitude": 36.57151
    },
    {
        "name": "Умм Ладж",
        "latitude": 25.02126,
        "longitude": 37.2685
    }
]