{
    "Total": {
        "1995": null,
        "1996": null,
        "1997": null,
        "1998": null,
        "1999": null,
        "2000": null,
        "2001": null,
        "2002": null,
        "2003": null,
        "2004": null,
        "2005": null,
        "2006": null,
        "2007": null,
        "2008": null,
        "2009": null,
        "2010": null,
        "2011": null,
        "2012": null,
        "2013": null,
        "2014": null,
        "2015": null,
        "2016": null,
        "2017": null,
        "2018": null,
        "2019": null,
        "2020": null,
        "2021": null
    },
    "Overnights visitors (tourists)": {
        "1995": null,
        "1996": 1337,
        "1997": 1635,
        "1998": 986,
        "1999": 1253,
        "2000": 1151,
        "2001": 1312,
        "2002": 1371,
        "2003": 1543,
        "2004": null,
        "2005": 1182,
        "2006": 1200,
        "2007": 1230,
        "2008": 1186,
        "2009": 1344,
        "2010": 1343,
        "2011": 1328,
        "2012": 1278,
        "2013": 1299,
        "2014": 1325,
        "2015": 1256,
        "2016": 1279,
        "2017": 1343,
        "2018": 1277,
        "2019": 1226,
        "2020": 345,
        "2021": 211
    },
    "Same-day visitors (excursionists)": {
        "1995": 300,
        "1996": 315,
        "1997": 269,
        "1998": 284,
        "1999": 289,
        "2000": 281,
        "2001": 283,
        "2002": 256,
        "2003": 461,
        "2004": 459,
        "2005": 837,
        "2006": 873,
        "2007": 869,
        "2008": 756,
        "2009": 908,
        "2010": 868,
        "2011": 879,
        "2012": 888,
        "2013": 968,
        "2014": 939,
        "2015": 873,
        "2016": 947,
        "2017": 921,
        "2018": 782,
        "2019": 680,
        "2020": 194,
        "2021": 170
    },
    "of which, cruise passengers": {
        "1995": null,
        "1996": null,
        "1997": null,
        "1998": null,
        "1999": null,
        "2000": null,
        "2001": null,
        "2002": null,
        "2003": null,
        "2004": null,
        "2005": 345,
        "2006": 327,
        "2007": 361,
        "2008": 430,
        "2009": 436,
        "2010": 475,
        "2011": 449,
        "2012": 390,
        "2013": 331,
        "2014": 386,
        "2015": 383,
        "2016": 332,
        "2017": 422,
        "2018": 496,
        "2019": 546,
        "2020": 152,
        "2021": 40
    }
}