{
    "Total": {
        "1995": null,
        "1996": null,
        "1997": null,
        "1998": null,
        "1999": null,
        "2000": null,
        "2001": null,
        "2002": null,
        "2003": null,
        "2004": null,
        "2005": null,
        "2006": null,
        "2007": null,
        "2008": null,
        "2009": null,
        "2010": null,
        "2011": null,
        "2012": null,
        "2013": null,
        "2014": null,
        "2015": null,
        "2016": null,
        "2017": null,
        "2018": null,
        "2019": null,
        "2020": null,
        "2021": null
    },
    "Overnights visitors (tourists)": {
        "1995": 1433,
        "1996": 751,
        "1997": 758,
        "1998": 823,
        "1999": 725,
        "2000": 707,
        "2001": 788,
        "2002": 661,
        "2003": 668,
        "2004": 840,
        "2005": 981,
        "2006": 2096,
        "2007": 2381,
        "2008": 2545,
        "2009": 2649,
        "2010": 1701,
        "2011": 2356,
        "2012": 2434,
        "2013": 2595,
        "2014": 2866,
        "2015": 3371,
        "2016": 3675,
        "2017": 4056,
        "2018": 4397,
        "2019": 4531,
        "2020": 1396,
        "2021": 2174
    },
    "Same-day visitors (excursionists)": {
        "1995": 1399,
        "1996": 631,
        "1997": 639,
        "1998": 674,
        "1999": 546,
        "2000": 557,
        "2001": 616,
        "2002": 567,
        "2003": 625,
        "2004": 791,
        "2005": 933,
        "2006": 2045,
        "2007": 2254,
        "2008": 2317,
        "2009": 2364,
        "2010": 1405,
        "2011": 2043,
        "2012": 2180,
        "2013": 2288,
        "2014": 2552,
        "2015": 3099,
        "2016": 3370,
        "2017": 3712,
        "2018": 4020,
        "2019": 4169,
        "2020": 1262,
        "2021": 2155
    },
    "of which, cruise passengers": {
        "1995": 34,
        "1996": 120,
        "1997": 119,
        "1998": 149,
        "1999": 179,
        "2000": 150,
        "2001": 172,
        "2002": 94,
        "2003": 43,
        "2004": 49,
        "2005": 48,
        "2006": 51,
        "2007": 127,
        "2008": 228,
        "2009": 285,
        "2010": 296,
        "2011": 313,
        "2012": 254,
        "2013": 307,
        "2014": 314,
        "2015": 272,
        "2016": 306,
        "2017": 345,
        "2018": 378,
        "2019": 362,
        "2020": 134,
        "2021": 19
    }
}