{
    "Total": {
        "1995": null,
        "1996": null,
        "1997": null,
        "1998": null,
        "1999": null,
        "2000": null,
        "2001": null,
        "2002": null,
        "2003": null,
        "2004": null,
        "2005": null,
        "2006": null,
        "2007": null,
        "2008": null,
        "2009": null,
        "2010": null,
        "2011": null,
        "2012": null,
        "2013": null,
        "2014": null,
        "2015": null,
        "2016": null,
        "2017": null,
        "2018": null,
        "2019": null,
        "2020": null,
        "2021": null
    },
    "Overnights visitors (tourists)": {
        "1995": null,
        "1996": 29,
        "1997": 38,
        "1998": 30,
        "1999": 36,
        "2000": 39,
        "2001": 38,
        "2002": 50,
        "2003": 52,
        "2004": 52,
        "2005": 61,
        "2006": 246,
        "2007": 328,
        "2008": 436,
        "2009": 440,
        "2010": 420,
        "2011": 495,
        "2012": 536,
        "2013": 575,
        "2014": 591,
        "2015": 684,
        "2016": 741,
        "2017": 800,
        "2018": 813,
        "2019": 836,
        "2020": null,
        "2021": null
    },
    "Same-day visitors (excursionists)": {
        "1995": null,
        "1996": null,
        "1997": null,
        "1998": null,
        "1999": null,
        "2000": null,
        "2001": null,
        "2002": null,
        "2003": null,
        "2004": null,
        "2005": null,
        "2006": null,
        "2007": null,
        "2008": null,
        "2009": null,
        "2010": null,
        "2011": null,
        "2012": null,
        "2013": null,
        "2014": null,
        "2015": null,
        "2016": null,
        "2017": null,
        "2018": null,
        "2019": null,
        "2020": null,
        "2021": null
    },
    "of which, cruise passengers": {
        "1995": null,
        "1996": null,
        "1997": null,
        "1998": null,
        "1999": null,
        "2000": null,
        "2001": null,
        "2002": null,
        "2003": null,
        "2004": null,
        "2005": null,
        "2006": null,
        "2007": null,
        "2008": null,
        "2009": null,
        "2010": null,
        "2011": null,
        "2012": null,
        "2013": null,
        "2014": null,
        "2015": null,
        "2016": null,
        "2017": null,
        "2018": null,
        "2019": null,
        "2020": null,
        "2021": null
    }
}