{
    "Total": {
        "1995": null,
        "1996": 745,
        "1997": 1004,
        "1998": 1170,
        "1999": 1416,
        "2000": 1603,
        "2001": 1774,
        "2002": 1775,
        "2003": 1686,
        "2004": 1906,
        "2005": 2049,
        "2006": 2319,
        "2007": 2221,
        "2008": 2152,
        "2009": 2348,
        "2010": 2430,
        "2011": 2532,
        "2012": 2716,
        "2013": 2847,
        "2014": 2862,
        "2015": 3014,
        "2016": 3540,
        "2017": 4009,
        "2018": 4654,
        "2019": 4712,
        "2020": 4276,
        "2021": 1086
    },
    "Overnights visitors (tourists)": {
        "1995": null,
        "1996": 742,
        "1997": 999,
        "1998": 1153,
        "1999": 1390,
        "2000": 1561,
        "2001": 1741,
        "2002": 1736,
        "2003": 1656,
        "2004": 1847,
        "2005": 2017,
        "2006": 2261,
        "2007": 2150,
        "2008": 2119,
        "2009": 2316,
        "2010": 2405,
        "2011": 2507,
        "2012": 2688,
        "2013": 2823,
        "2014": 2839,
        "2015": 2981,
        "2016": 3506,
        "2017": 3975,
        "2018": 4594,
        "2019": 4684,
        "2020": 4263,
        "2021": 1085
    },
    "Same-day visitors (excursionists)": {
        "1995": null,
        "1996": 3,
        "1997": 5,
        "1998": 17,
        "1999": 26,
        "2000": 42,
        "2001": 33,
        "2002": 39,
        "2003": 30,
        "2004": 59,
        "2005": 32,
        "2006": 58,
        "2007": 71,
        "2008": 33,
        "2009": 32,
        "2010": 25,
        "2011": 25,
        "2012": 28,
        "2013": 24,
        "2014": 23,
        "2015": 33,
        "2016": 34,
        "2017": 34,
        "2018": null,
        "2019": null,
        "2020": null,
        "2021": null
    },
    "of which, cruise passengers": {
        "1995": null,
        "1996": 1,
        "1997": 2,
        "1998": 2,
        "1999": 8,
        "2000": 4,
        "2001": 10,
        "2002": 14,
        "2003": 6,
        "2004": 20,
        "2005": 5,
        "2006": 17,
        "2007": 30,
        "2008": 7,
        "2009": 5,
        "2010": 4,
        "2011": 2,
        "2012": 1,
        "2013": 3,
        "2014": 2,
        "2015": 8,
        "2016": 10,
        "2017": 17,
        "2018": null,
        "2019": null,
        "2020": null,
        "2021": null
    }
}