{
    "Accommodation for visitors in hotels and similar establishments": {
        "1995": null,
        "1996": null,
        "1997": null,
        "1998": null,
        "1999": null,
        "2000": null,
        "2001": null,
        "2002": null,
        "2003": null,
        "2004": null,
        "2005": null,
        "2006": null,
        "2007": null,
        "2008": null,
        "2009": null,
        "2010": null,
        "2011": null,
        "2012": null,
        "2013": null,
        "2014": null,
        "2015": 24,
        "2016": 31,
        "2017": 30,
        "2018": 31,
        "2019": 31,
        "2020": 22,
        "2021": null
    },
    "Number of establishments": {
        "1995": null,
        "1996": null,
        "1997": null,
        "1998": 158,
        "1999": 158,
        "2000": 158,
        "2001": 158,
        "2002": 162,
        "2003": 162,
        "2004": null,
        "2005": null,
        "2006": null,
        "2007": null,
        "2008": null,
        "2009": null,
        "2010": null,
        "2011": null,
        "2012": null,
        "2013": null,
        "2014": null,
        "2015": 306,
        "2016": 362,
        "2017": 340,
        "2018": 322,
        "2019": 391,
        "2020": 221,
        "2021": null
    },
    "Number of rooms": {
        "1995": null,
        "1996": null,
        "1997": null,
        "1998": 309,
        "1999": 309,
        "2000": 309,
        "2001": 309,
        "2002": null,
        "2003": null,
        "2004": null,
        "2005": null,
        "2006": null,
        "2007": null,
        "2008": null,
        "2009": null,
        "2010": null,
        "2011": null,
        "2012": null,
        "2013": null,
        "2014": null,
        "2015": 612,
        "2016": 571,
        "2017": 674,
        "2018": 627,
        "2019": 683,
        "2020": 332,
        "2021": null
    },
    "Number of bed-places": {
        "1995": null,
        "1996": null,
        "1997": null,
        "1998": null,
        "1999": null,
        "2000": null,
        "2001": null,
        "2002": null,
        "2003": null,
        "2004": null,
        "2005": null,
        "2006": null,
        "2007": null,
        "2008": null,
        "2009": null,
        "2010": null,
        "2011": null,
        "2012": null,
        "2013": null,
        "2014": null,
        "2015": null,
        "2016": null,
        "2017": null,
        "2018": null,
        "2019": null,
        "2020": null,
        "2021": null
    },
    "Occupancy rate / rooms": {
        "1995": null,
        "1996": null,
        "1997": null,
        "1998": null,
        "1999": null,
        "2000": null,
        "2001": null,
        "2002": null,
        "2003": null,
        "2004": null,
        "2005": null,
        "2006": null,
        "2007": null,
        "2008": null,
        "2009": null,
        "2010": null,
        "2011": null,
        "2012": null,
        "2013": null,
        "2014": null,
        "2015": null,
        "2016": null,
        "2017": null,
        "2018": null,
        "2019": null,
        "2020": null,
        "2021": null
    },
    "Occupancy rate / bed-places": {
        "1995": 19,
        "1996": 21,
        "1997": 21,
        "1998": 18,
        "1999": 7,
        "2000": 7,
        "2001": 7,
        "2002": null,
        "2003": null,
        "2004": null,
        "2005": null,
        "2006": null,
        "2007": null,
        "2008": null,
        "2009": null,
        "2010": null,
        "2011": null,
        "2012": null,
        "2013": null,
        "2014": null,
        "2015": null,
        "2016": null,
        "2017": null,
        "2018": null,
        "2019": null,
        "2020": null,
        "2021": null
    },
    "Average length of stay": {
        "1995": null,
        "1996": null,
        "1997": null,
        "1998": null,
        "1999": null,
        "2000": null,
        "2001": null,
        "2002": null,
        "2003": null,
        "2004": null,
        "2005": null,
        "2006": null,
        "2007": null,
        "2008": null,
        "2009": null,
        "2010": null,
        "2011": null,
        "2012": null,
        "2013": null,
        "2014": null,
        "2015": null,
        "2016": null,
        "2017": null,
        "2018": null,
        "2019": null,
        "2020": null,
        "2021": null
    }
}